archon/__init__.py
archon/exceptions.py
archon/tools.py
archon/actor/__init__.py
archon/actor/actor.py
archon/actor/delegate.py
archon/actor/recovery.py
archon/actor/tools.py
archon/actor/commands/__init__.py
archon/actor/commands/config.py
archon/actor/commands/disconnect.py
archon/actor/commands/expose.py
archon/actor/commands/flush.py
archon/actor/commands/frame.py
archon/actor/commands/init.py
archon/actor/commands/power.py
archon/actor/commands/reconnect.py
archon/actor/commands/recover.py
archon/actor/commands/reset.py
archon/actor/commands/status.py
archon/actor/commands/system.py
archon/actor/commands/talk.py
archon/actor/commands/window.py
archon/controller/__init__.py
archon/controller/command.py
archon/controller/controller.py
archon/controller/maskbits.py
archon/etc/archon.yml
archon/etc/schema.json
sdss_archon-0.15.5.dist-info/METADATA
sdss_archon-0.15.5.dist-info/WHEEL
sdss_archon-0.15.5.dist-info/licenses/LICENSE.md
sdss_archon-0.15.5.dist-info/RECORD
