Metadata-Version: 2.4
Name: sdss-archon
Version: 0.15.5
Summary: A library and actor to communicate with an STA Archon controller.
Project-URL: Homepage, https://github.com/sdss/archon
Project-URL: Repository, https://github.com/sdss/archon
Project-URL: Documentation, https://sdss-archon.readthedocs.org
Author-email: José Sánchez-Gallego <gallegoj@uw.edu>
License: BSD-3-Clause
License-File: LICENSE.md
Requires-Python: <4,>=3.10
Requires-Dist: astropy>=6.0
Requires-Dist: click-default-group>=1.2.2
Requires-Dist: numpy>=2.0.0
Requires-Dist: sdss-clu>=2.5.3
Requires-Dist: sdsstools>=1.9.1
Provides-Extra: fitsio
Requires-Dist: fitsio>=1.2.2; extra == 'fitsio'
